{
    "game_id": 2,
    "post_id": "51947575",
    "f_forum_id": 43,
    "subject": "【仆人测评】这0命无专武仆人普攻伤害就离谱！",
    "url": "https://www.miyoushe.com/ys/article/51947575",
    "created_at": 1713958895,
    "like_num": 4520,
    "view_num": 21807,
    "reply_num": 278,
    "text": "省流： 仆人，90级，零命，精一鸟枪，四角斗士，天赋8，6，6，暴击63.6， 爆伤240.7，攻击力2373 单人65契，普攻伤害为1w3到1w9左右，大招3w7 单人130契，普攻伤害为1w3到2w6左右 裸蒸65契，普攻伤害为1w3到2w4左右，大招5w5 裸蒸130契，普攻伤害为1w4到3w4左右 纯火队(仆班钟万) 输出流程：仆人e班尼特eq钟离e万叶e仆人重击普攻战场qe下场 普攻伤害为5w6到8w5左右，大招10w4左右 超载队(仆皇夏班) 输出流程：皇女e仆人e夏沃蕾长e皇女q班尼特eq仆人重击普攻战场q e下场 普攻伤害为4w3到6w7左右，大招9w5左右 蒸发队(仆叶万班) 输出流程：仆人e夜兰eq班尼特eq万叶e仆人重击平a，qe下场 普攻伤害为6w到14w，大招12w2左右 一套半个枫丹传奇，约一百万总伤，我感觉挺不错了 友友们视频制作不易，给个免费的赞吧",
    "length": 395
}