{
    "game_id": 2,
    "post_id": "45351565",
    "f_forum_id": 43,
    "subject": "《浪影阔剑武器攻略》枫丹锻造系列武器",
    "url": "https://www.miyoushe.com/ys/article/45351565",
    "created_at": 1699617086,
    "like_num": 53,
    "view_num": 20712,
    "reply_num": 52,
    "text": "浪影阔剑90级基础攻击力510，副词条增加攻击力41.3%。在精炼5阶的情况下：受治疗后，攻击力提升48%，持*8*。无冷却时间，可以无限续杯，角色处于后台也能触发。角色的治疗技能和回复类的料理都能触发武器特效。即使角色满血只要在接受治疗，同样可以触发。但神像的恢复效果不能触发武器特效。 浪影阔剑的武器特效非常简单粗暴易触发，也没有 「 生命之契 」这样的DeBuff。作为一把锻造武器强度完全在线。目前所有攻击型模的大剑角色都是能用的。菲米尼，迪希雅，优菈，迪卢克，重云，雷泽都是完全适适配这把武器的。 北斗虽然也能用浪影阔剑，但到了游戏中后期更推荐北斗玩副C流，用绝缘套配加充能武器的配装。 卡维主打绽放反应，大招所需能量80点充能缺口较大，推荐精通或者充能类型的武器。多莉的大招所需能量也是80点，充能缺口较大，又身为辅助角色，推荐充能类型的武器。一斗和满命女仆有防御转攻击的模型，在锻造武器中则更推荐防御副词条的白影剑。优菈虽然是主打物理伤害的角色，也有加物理伤害的锻造武器。但雪葬的星银作为一把1.2版本就上线的武器，武器特效实在过于孱弱。如果你的优菈确实没有其他合适武器，需要锻造一把武器的话，也推荐这把 浪影阔剑，外观方面和优菈也非常的搭，和专武相比也毫不逊色。 浪影阔剑的强度和颜值都是非常棒的。但我看着包里已经拉满并且精炼5阶的浪影阔剑陷入了沉思，我已经多久没有用大剑角色打过深渊后面2层了？是我一个人很少用大剑角色打深渊了？还是大家都很少用大剑角色打深渊了？",
    "length": 640
}