{
    "game_id": 2,
    "post_id": "47223954",
    "f_forum_id": 43,
    "subject": "【V4.3攻略】究极霸王超级魔剑——武器测评",
    "url": "https://www.miyoushe.com/ys/article/47223954",
    "created_at": 1703921959,
    "like_num": 663,
    "view_num": 18370,
    "reply_num": 64,
    "text": "Hello大家好这里是blue~ 这次给大家带来4.3活动赠送武器——究极霸王超级魔剑的攻略测评，极霸剑表现到底如何呢，我们一起来看一下吧~ 究极霸王超级魔剑，贴纸特效获取攻略（美露莘任务一览） 武器简评 究极霸王超级魔剑是565白值，主词条为充能效率的双手剑。 属于高白值低词条量的武器，这种数值模型会让武器攻击性的比重更高，充能词条减少，也就是功能性比重下降。综合来看还是早柚更契合，充能给的不多不少，还可以有一定攻击词条提高治疗量。 武器被动最高给了48%的攻击，是比较高的数值，相比精1无工之剑满层都多了8%，只可惜主词条是充能，都否则又是一个四星数值怪。 进阶分析 对极霸剑的表现进行了简单计算，娜维娅用满层E做参考，早柚则用大招治疗量做参考。 可以看到，对于娜维娅而言，极霸剑的表现还是低于螭骨的，但极霸剑领先一个充能，在不打算买大月卡的时候可以就给娜维娅使用极霸剑，效果说得过去，外观也能毕业。 对于早柚而言，极霸剑确实是四星中属性较为不错的选择，如果仓库里没有别的选择（比如狼末），或是武器受到其它角色占用，可以考虑给早柚一把。 总结 究极霸王超级魔剑和往常的活动赠送武器一样，以收藏价值为主。且其与世界任务的梅露辛有一定联动，更有故事感，作为收藏纪念品确实比较优秀。 实战方面在你的娜维娅没有更合适的武器时，可以使用；或是直接给早柚进行一个装备。",
    "length": 582
}