{
    "game_id": 2,
    "post_id": "34327261",
    "f_forum_id": 43,
    "subject": "一把被低估的武器：风信之锋",
    "url": "https://www.miyoushe.com/ys/article/34327261",
    "created_at": 1673879973,
    "like_num": 57,
    "view_num": 16258,
    "reply_num": 47,
    "text": "说到被低估的武器，你第一个想到谁？我的话， 风信之锋 。（先看完，误怼） 不会还有小伙伴不知道是哪把武器吧，是它啦， 别问为什么up没拉满，因为我有护摩嘿嘿。 属性介绍 当然今天要介绍的主角还是风信之锋了，先来介绍一下它的属性， 基础攻击力 ：1级42， 90级510 ，中规中矩 副词条 ：1级9%攻击力， 90级41.3%攻击力 ，很不错 特效 ：触发元素反应后的10秒内，攻击力提升12%/15%/18%/21%/24%，元素精通提升48/60/72/84/96点，还是很不错 既然在各方面都还不错的情况下，又是活动武器，为什么用的人少，没人推荐呢？ 下面说这个问题，首先第一点！ 枪系内卷太严重了！！！ 护摩把枪系卷上天了，然后卷不过护摩的其他枪系都发扬“特长“”去了，比如薙刀，息灾，四星这边决斗肯定是很多人的首选，高贵的暴击词条，又是月卡武器，相对容易获得。作为活动限定的风信，即使在各项 数值还不错 的情况下，依旧没有什么用武之地。 好，又有人问了，那up你不是说它是被低估的武器吗？看你的这番话像是贬低这把武器啊 。 别急，我继续说， 风信之锋这把武器的定位并不是给想要提升的人使用的，而是作为过渡武器，新手入门，没有合适武器的人使用的 。（我愿称之过渡滴神） 先说风信能过渡那些角色， 赛诺，胡桃，魈，香菱，申鹤等 。下面举几个例子，①在没有决斗或者决斗有人使用的情况下，风信就可以作为替补上场；②申鹤没有息灾和断浪长鳍的情况下风信再合适不过；③赛诺在没有其他五星和决斗的情况下在合适不过；④魈在没有五星和决斗的情况下很合适。这么一说你是不是觉得风信之锋有用了呢？ 欢迎评论区讨论",
    "length": 699
}