{
    "game_id": 2,
    "post_id": "42526922",
    "f_forum_id": 43,
    "subject": "枫丹4.0一条龙全收集",
    "url": "https://www.miyoushe.com/ys/article/42526922",
    "created_at": 1692333468,
    "like_num": 624,
    "view_num": 27704,
    "reply_num": 50,
    "text": "点击蓝色字体就可以进入对应视频啦！ 第一集 【枫丹4.0一条龙全收集】主线必拿的11个宝箱(1-11)成就数11 神瞳1-3 原神4.0枫丹廷 苍晶区 白露区 神秘的书页 神秘的核心 探索度 第二集 【枫丹4.0一条龙全收集】同步主线宝箱 共4个(8-11)成就数11 神瞳2-3 原神4.0枫丹廷 苍晶区 白露区 神秘的书页 神秘的核心 探索度 第三集 【枫丹4.0一条龙全收集】海露港 共4个(12-15)成就数15 神瞳4-5 原神4.0枫丹廷 苍晶区 白露区 神秘的书页 神秘的核心 探索度 第四集 【枫丹4.0一条龙全收集】秋分山西侧(1) 共17个(16-32)成就数32 神瞳6-12 神秘的核心1 好东西坏品味1 原神4.0枫丹廷 苍晶区 白露区 神秘的书页 神秘的核心 探索度 第五集 【枫丹4.0一条龙全收集】秋分山西侧(2) 共8个(33-40)成就数40 神瞳13 好东西坏品味2 原神4.0枫丹廷 苍晶区 白露区 神秘的书页 神秘的核心 探索度 第六集 【枫丹4.0一条龙全收集】白淞镇 共8个(41-48)成就数48 神瞳14-18 原神4.0枫丹廷 苍晶区 白露区 神秘的书页 神秘的核心 探索度 第七集 【枫丹4.0一条龙全收集】海沫村 共32个(49-80)成就数80 神瞳19-22 神秘的书页13 原神4.0枫丹廷 苍晶区 白露区 神秘的书页 神秘的核心 探索度 第八集 【枫丹4.0一条龙全收集】苍晶区(1) 共17个(81-97)成就数97 神瞳23-25 神秘的核心2 原神4.0枫丹廷 苍晶区 白露区 神秘的书页 神秘的核心 探索度 第九集 【枫丹4.0一条龙全收集】苍晶区(2) 共14个(98-111)成就数111 神瞳26-27 好东西坏品味3 原神4.0枫丹廷 苍晶区 白露区 神秘的书页 神秘的核心 探索度 第十集 【枫丹4.0一条龙全收集】苍晶区(3) 共9个(112-120)成就数120 神瞳28-29 原神4.0枫丹廷 苍晶区 白露区 神秘的书页 神秘的核心 探索度 第十一集 【枫丹4.0一条龙全收集】苍晶区(4) 共12个(121-132)成就数132 神瞳30-35 神秘的核心3 原神4.0枫丹廷 苍晶区 白露区 神秘的书页 神秘的核心 探索度 第十二集 【枫丹4.0一条龙全收集】苍晶区(5) 共11个(133-143)成就数143 神瞳36-40 好东西坏品味4 原神4.0枫丹廷 苍晶区 白露区 神秘的书页 神秘的核心 探索度 第十三集 【枫丹4.0一条龙全收集】埃尔顿海沟(1) 共8个(144-151)成就数151 神瞳41-46 原神4.0枫丹廷 苍晶区 白露区 神秘的书页 神秘的核心 探索度 第十四集 【枫丹4.0一条龙全收集】埃尔顿海沟(2) 共16个(152-167)成就数167 神瞳47-50 神秘的核心4 原神4.0枫丹廷 苍晶区 白露区 神秘的书页 神秘的核心 探索度 第十五集 【枫丹4.0一条龙全收集】希望之路 共20个(168-187)成就数187 神瞳51-53 原神4.0枫丹廷 苍晶区 白露区 神秘的书页 神秘的核心 探索度 第十六集 【枫丹4.0一条龙全收集】安眠处 共12个(188-199)成就数199 神瞳54-55 神秘的书页7、9 原神4.0枫丹廷 苍晶区 白露区 神秘的书页 神秘的核心 探索度 第十七集 【枫丹4.0一条龙全收集】自然哲学学院 共13个(200-212)成就数210 神瞳56-58 神秘的书页4、5、6、8、11 原神4.0枫丹廷 苍晶区 白露区 神秘的书页 神秘的核心 探索度 第十八集 【枫丹4.0一条龙全收集】塞洛海原(1) 共10个(213-222)成就数220 神瞳59-63 原神4.0枫丹廷 苍晶区 白露区 神秘的书页 神秘的核心 探索度 第十九集 【枫丹4.0一条龙全收集】塞洛海原(2) 共9个(223-231)成就数229 神瞳64-65 原神4.0枫丹廷 苍晶区 白露区 神秘的书页 神秘的核心 探索度 第二十集 【枫丹4.0一条龙全收集】塞洛海原(3) 共10个(232-241)成就数239 神瞳66-68 神秘的核心5 原神4.0枫丹廷 苍晶区 白露区 神秘的书页 神秘的核心 探索度 第二十一集 【枫丹4.0一条龙全收集】塞洛海原(4) 共19个(242-260)成就数258 神瞳69-71 神秘的核心6、7 原神4.0枫丹廷 苍晶区 白露区 神秘的书页 神秘的核心 探索度 第二十二集 【枫丹4.0一条龙全收集】259华丽宝箱缺失解决方案 原神4.0枫丹廷 苍晶区 白露区 神秘的书页 神秘的核心 探索度 第二十三集 【枫丹4.0一条龙全收集】塔拉塔海谷 共13个(261-273)成就数271 神瞳72-73 原神4.0枫丹廷 苍晶区 白露区 神秘的书页 神秘的核心 探索度 第二十四集 【枫丹4.0一条龙全收集】茉洁站 共6个(274-279)成就数277 神瞳74-75 原神4.0枫丹廷 苍晶区 白露区 神秘的书页 神秘的核心 探索度 第二十五集 【枫丹4.0一条龙全收集】枫丹廷(1) 共16个(280-295)成就数293 神瞳76-82 好东西坏品味5、续 原神4.0枫丹廷 苍晶区 白露区 神秘的书页 神秘的核心 探索度 第二十六集 【枫丹4.0一条龙全收集】枫丹廷(2) 共13个(296-308)成就数306 神瞳83-85 原神4.0枫丹廷 苍晶区 白露区 神秘的书页 神秘的核心 探索度 第二十七集 【枫丹4.0一条龙全收集】枫丹廷(3) 共12个(309-320)成就数318 原神4.0枫丹廷 苍晶区 白露区 神秘的书页 神秘的核心 探索度 第二十八集 【枫丹4.0一条龙全收集】揭示之书 共10个(321-330)成就数328 神秘的书页12 原神4.0枫丹廷 苍晶区 白露区 神秘的书页 神秘的核心 探索度 第二十九集 【枫丹4.0一条龙全收集】依旧让人垂涎欲滴 共2个(331-332)成就数330 神秘的核心使用处 原神4.0枫丹廷 苍晶区 白露区 神秘的书页 神秘的核心 探索度 第三十集 【枫丹4.0一条龙全收集】地灵龛 共4个(333-336)成就数334 原神4.0枫丹廷 苍晶区 白露区 神秘的书页 神秘的核心 探索度 第三十一集 【枫丹4.0一条龙全收集】联机宝箱 共1个(337)成就数335 需联机 原神4.0枫丹廷 苍晶区 白露区 神秘的书页 神秘的核心 探索度 第三十二集 【枫丹4.0一条龙全收集】鸽子宝箱 共1个(338)成就数336 原神4.0枫丹廷 苍晶区 白露区 神秘的书页 神秘的核心 探索度 第三十三集 【枫丹4.0一条龙全收集】呜呜葡萄 共1个(339)成就数337 原神4.0枫丹廷 苍晶区 白露区 神秘的书页 神秘的核心 探索度 第三十四集 【枫丹4.0一条龙全收集】清理浮标 共1个(340)成就数338 原神4.0枫丹廷 苍晶区 白露区 神秘的书页 神秘的核心 探索度 第三十五集 【枫丹4.0一条龙全收集】4.1新增宝箱 共2个(341-342)成就数340 原神4.0枫丹廷 苍晶区 白露区 神秘的书页 神秘的核心 探索度 第三十六集 【枫丹4.0一条龙全收集】4.2新增宝箱 共4个(343-346)成就数344 原神4.0枫丹廷 苍晶区 白露区 神秘的书页 神秘的核心 探索度 第三十七集 【枫丹4.0一条龙全收集】金属盒1、枫丹廷 共4个(1-4)算探索度 原神4.0枫丹廷 苍晶区 白露区 神秘的书页 神秘的核心 探索度 第三十八集 【枫丹4.0一条龙全收集】金属盒2、安眠处 共26个(5-30)算探索度 原神4.0枫丹廷 苍晶区 白露区 神秘的书页 神秘的核心 探索度 第三十九集 【枫丹4.0一条龙全收集】金属盒3、自然哲学学院 共2个(31-32)算探索度 原神4.0枫丹廷 苍晶区 白露区 神秘的书页 神秘的核心 探索度 第四十集 【枫丹4.0一条龙全收集】金属盒4、希望之路 共8个(33-40)算探索度 原神4.0枫丹廷 苍晶区 白露区 神秘的书页 神秘的核心 探索度 第四十一集 【枫丹4.0一条龙全收集】金属盒5、塞洛海原 共16个(41-56)算探索度 原神4.0枫丹廷 苍晶区 白露区 神秘的书页 神秘的核心 探索度 第四十二集 【枫丹4.0一条龙全收集】金属盒6、塔拉塔海谷 共6个(57-62)算探索度 原神4.0枫丹廷 苍晶区 白露区 神秘的书页 神秘的核心 探索度 第四十三集 【枫丹4.0一条龙全收集】金属盒7、埃尔顿海沟上方 共12个(63-74)算探索度 原神4.0枫丹廷 苍晶区 白露区 神秘的书页 神秘的核心 探索度 第四十四集 【枫丹4.0一条龙全收集】金属盒8、埃尔顿海沟下方 共13个(75-87)摩拉盒1-4 算探索度 原神4.0枫丹廷 苍晶区 白露区 神秘的书页 神秘的核心 探索度 第四十五集 【枫丹4.0一条龙全收集】金属盒9、其他地区 共7个(88-94)算探索度 原神4.0枫丹廷 苍晶区 白露区 神秘的书页 神秘的核心 探索度 第四十六集 【枫丹4.0一条龙全收集】摩拉盒(1) 共12个(5-16)算探索度 原神4.0枫丹廷 苍晶区 白露区 神秘的书页 神秘的核心 探索度 第四十七集 【枫丹4.0一条龙全收集】摩拉盒(2) 共1个(17)算探索度 原神4.0枫丹廷 苍晶区 白露区 神秘的书页 神秘的核心 探索度 宝箱346（成就数344） （有两个宝箱不计入成就数） (4.1新增两个  4.2新增4个) 神瞳：85 仙灵：42 世界挑战：53 金属盒 ：157 水箱子 ：23 有帮助的话请点赞收藏支持一下谢谢！",
    "length": 4026
}