{
    "game_id": 2,
    "post_id": "45251225",
    "f_forum_id": 43,
    "subject": "精灵系列四，在伊黎耶深处（成就：无影的塞谟奈）",
    "url": "https://www.miyoushe.com/ys/article/45251225",
    "created_at": 1699421648,
    "like_num": 1421,
    "view_num": 31360,
    "reply_num": 49,
    "text": "大家好呀，这里是祈鸢，本期给大家带来的是4.2版本， 莫尔泰区 中的世界任务：在伊黎耶深处 任务概述 ：集齐3把水滴钥匙，开启广场下的密道，清除蛀食树根的孽瘤 任务奖励 ： 1个华丽/珍贵/精致/普通宝箱 ，1个成就（无影的塞谟奈） 预计用时 ：10分钟 注意事项 ： （1）算是 开图任务 之一，建议 优先完成 （2）这篇是「 伊黎耶的野精灵 」系列任务的 第四阶段 ， 后续的链接 放在了文末 （3） 第三阶段 任务详见该帖 精灵系列三，愤怒泉眼 1，返回 茉洁站 喷泉处，将3个 水滴钥匙 放入雕像 2，进入喷泉下的 密道 ，向下游到底，可以获得一个 华丽宝箱 3，之后进入面前的 漩涡 ，顺着水道前进 4，来到东边的 洞窟 ，先击败下方全部的 兽境猎犬 5，再吸收 章鱼 的力量，先清除3个小 菌毯 ，再清除中间的大 菌毯 6，之后会召唤很多 菌毯 出来，我们一样是先清完小 菌毯 ，再清除大 菌毯 7，最后击败出现的 兽境猎犬 ，顺着 洋流 离开洞窟 8，任务完结，开启水中的 全部宝箱 （包括摩拉箱） 即可获得 成就《无影的塞谟奈》 9，顺便说一下，做完任务后，湖中间的的大树旁会长出一些 湖光铃兰 ， 部分点位 由1朵变为2朵 10，再顺便说一下，来到优兰尼娅湖北边的洞窟，可以找到 珀西芙 和一个 珍贵宝箱 11，对话可以接一个 隐藏任务 ，任务攻略详见链接 隐藏任务，幽灵枝（成就：明天交换明天）",
    "length": 607
}