{
    "game_id": 2,
    "post_id": "45421702",
    "f_forum_id": 43,
    "subject": "【隐藏成就】未祛魅的世界（神秘的异色结晶石）",
    "url": "https://www.miyoushe.com/ys/article/45421702",
    "created_at": 1699771262,
    "like_num": 56,
    "view_num": 4221,
    "reply_num": 9,
    "text": "各位好啊，这里是葡萄_(菲米尼-冒泡)带来4.2隐藏成就 【未祛魅的世界】 相关记录。 前置:需完成 藻海 系列任务与「伊黎耶的野精灵」。 耗费时间: 三天 ①第一天 （✓） 我们来到 莫尔泰区 的自身之塔塔底，就能见到地方传奇「 夏萨尼翁 」。利用章鱼的能力，如下面第二张图，等它释放透明泡泡，打回去。其他时间，可以躲到上方大齿轮夹隙，规避水泡爆炸造成的大范围高伤害 _(菲米尼-冒泡) 打了两次，发现可利用章鱼的能力长按把它的水泡反弹回去，当它吐出3个泡泡时会进入释放泡泡的状态。此方法适合手法娴熟，不怕掉血的玩家（旁边游鱼可回血）。 第一次打完，几乎全军覆没_(心情简单)首次击杀会获得成就 【夏萨尼翁】 ，且会掉落一枚神秘的异色结晶石头。 注: 每日只会掉落一枚，记得及时去找「锈舵」的皮托提交。 ②第二天 （✓） ③第三天 （✓） 提交第三个结晶石，即可获取成就 【未祛魅的世界】 更新完毕，下期见_(瑶瑶-笑一个)",
    "length": 413
}