{
    "game_id": 2,
    "post_id": "39430007",
    "f_forum_id": 43,
    "subject": "素材之旅，愚人众精英怪全收录篇（讨债人镜女萤术士）",
    "url": "https://www.miyoushe.com/ys/article/39430007",
    "created_at": 1684313119,
    "like_num": 158,
    "view_num": 9416,
    "reply_num": 11,
    "text": "旅行者，你们好，今天带来的是愚人众精英怪锄大地路线分享，收录了截至4.0枫丹版本以来的全部愚人众精英怪，即萤术士、债务处理人和藏镜仕女，一起来看下吧。_(瑶瑶-出来玩) 目录： 一、前言：关于愚人众精英怪的小知识 二、愚人众精英怪路线篇 三、结尾 一、前言：关于愚人众精英怪的小知识 该路线推荐玩家：缺少愚人众阵营势力相关素材的玩家，结合起来一起刷，可以自行选择 债务处理人、藏镜仕女和萤术士属于200摩拉精英怪，掉落物为武器突破素材 关于刷新时间：每天凌晨4点刷新，精英怪上限400只，超出无法获取摩拉与素材 关于阵容：推荐带上抗打断角色+双风，讨债人秒人的_(提纳里-趴) 掉落物： 尉官的徽记、士官的徽记、新兵的徽记 债务处理人：猎兵祭刀、特工祭刀、特工祭刀 藏镜仕女：黯淡棱镜、水晶棱镜、偏光棱镜 萤术士：雾虚花粉、雾虚草囊、雾虚灯芯 二、愚人众精英怪路线篇 愚人众精英怪目前每个国家均有分布，枫丹也有哦，其中讨债人主要在璃月须弥，萤术士在蒙德雪山和稻妻鸣神岛，镜女在稻妻。讨债人总共有29只，萤术士总共有44只，藏镜仕女总共有36只。 重要提示： 黄色路线 为高效率刷取路线、推荐去； 蓝色路线 为普通效率刷取路线、可以酌情选择去或不去； 白色路线 为低效率刷取路线，仅当作收录，不推荐去（当然你时间多想跑一趟也行） 路线一 蒙德&雪山 路线二 雪山&璃月 路线三 璃月 路线四 璃月&地下矿区 路线五 稻妻鸣神岛&神无冢 路线六 稻妻神无冢&八酝岛 路线七 海祇岛&清籁岛 路线八 清籁岛&须弥雨林 路线九 须弥 路线十 须弥沙漠 路线十一 须弥沙漠 路线十二 枫丹 三、结尾 感谢各位旅行者们的观看，喜欢的话不妨为我点个赞哦，咱们下一篇攻略再见_(柯莱-心里乱)",
    "length": 738
}