{
    "game_id": 2,
    "post_id": "55390536",
    "f_forum_id": 43,
    "subject": "希穆兰卡星轨王城    宝箱、悠乐片段及解密 ［一］",
    "url": "https://www.miyoushe.com/ys/article/55390536",
    "created_at": 1721409762,
    "like_num": 99,
    "view_num": 12666,
    "reply_num": 18,
    "text": "本篇内容包括4.8版本活动限时地图「希穆兰卡」中 星轨王城 的部分宝箱、悠乐片段、限时机关挑战、解密等内容。（制作不易，如有纰漏，还请见谅～）_(纳西妲-开心) 希穆兰卡星轨王城  宝箱、悠乐片段及解密 ［二］ 六芒星 —— 欢声飞羽     铁镐 —— 限时挑战 怪物头像 —— 宝箱      旗帜 —— 趣味挑战 地图1号位置， 操控飞鼠钻过所有花圈 即可胜利，获得一个精致的宝箱。 地图2号位置，让积木小人们有序排队，先 攻击发条让时间逆流回最初 ，然后按照图中连法连接魔线即可，获得一个精致的宝箱。 地图3号位置，首先找到 发条电梯 ，到达高处平台然后 魔线飞行 至悬空平台上。进行 限时挑战 后获得一个珍贵的宝箱。 然后，视角转至东北，降落到此处平带台上，可以获得一个普通的宝箱。 地图4号位置，给小人拍照，获得一个摩拉箱。 地图5号位置，需要与积木小人们玩 捉迷藏 ，三个小人的位置如下，其中黄色小人藏在草丛中，使用普攻清除后可更为容易地找到。 地图6号位置，靠近后自动触发。首先 攻击发条让时间逆流回最初 ，然后 攻击胶水大炮3下 ，黏住红色小人即可获得一个珍贵的宝箱。 地图7号位置，与积木小人玩 一二三木头人 ，胜利后获得一个精致的宝箱。 地图8号位置，靠近自动触发「你画我踩」。先打 2下 发条，让小人踩在 红色机关 上，然后不要动发条小人会自动后退，踩到一次 蓝色机关 ，最后攻击 1下 发条，让小人再次踩在 蓝色机关 上，获得一个精致的宝箱。 地图9号位置，乘坐发条电梯到达高层平台后给小人拍照，获得一个摩拉箱。 地图10号位置，将三个小人从胶水中解救出来，即可获得一个普通的宝箱。 向前跳下平台，还可以拍照，获得一个摩拉箱。 地图11号位置，靠近后自动触发「高空落物」。首先 击破阻拦红色小人的箱子 ，然后使用胶水大炮将落下来的方块底部粘上胶水，最后 攻击发条让时间逆流回最初 ，就会发现方块被粘住，无法掉落，获得一个珍贵的宝箱。 地图12号位置，与小人玩 一二三木头人 ，胜利后获得一个精致的宝箱。 地图13号位置，找到胖胖鼠，向其交付一个泡泡橘，即可获得奖励。 好啦，各位旅行者大人，这次的攻略就到这里啦，下次，我们再见!_(派蒙-拜拜)_(派蒙-拜拜) 由于星轨王城里面解密以及宝箱太密集了，但是地图却不能无限放大，所以标识位置可能有点偏差，还请旅行者大人们不要苛责，多多包容～_(瑶瑶-拜托了)_(瑶瑶-拜托了)",
    "length": 1024
}