{
    "game_id": 2,
    "post_id": "44714056",
    "f_forum_id": 43,
    "subject": "【MSTAR三周年】水仙的安·第三幕+后续",
    "url": "https://www.miyoushe.com/ys/article/44714056",
    "created_at": 1697870336,
    "like_num": 121,
    "view_num": 8696,
    "reply_num": 23,
    "text": "各位旅行者大家好，这里是烟雨，本篇给大家带来的是世界任务【水仙的安·第三幕】及后续和【古老的颜色】的后续任务_(米游姬-来了来了) 任务限制：完成【水色潮痕】【水仙的安】【古老的颜色】 任务奖励：40原石+3个隐藏成就 【假如她不会再梦到你】： 进入梦境后，我们前往寻找声音的主人 对话结束后，我们跟随玛丽安参观她的花园 然后我们要给［好狗狗］喂食，随后我们倾听玛丽安的故事，揭开“安”的故事的真相 然后玛丽安会把我们送出梦境，动画结束后，我们顺着洋流回到高塔 然后与安对话，得知［水十字军结社］这个地方 对话结束后完成任务获得一个华丽宝箱以及隐藏成就【不可思议之国的安】 【水仙的安】后续： 我们来到自然哲学院，往里走直至尽头，阅读桌上的书，我们会来到水十字军结社的集会所，自动触发两个后续任务并获得成就【自然哲学百科全书】 我们先与安对话，待剧情对话结束后完成后续“尚未完结的故事” 【古老的颜色】后续： 我们前往桌子处与西摩尔对话，问完所有问题后就完成了后续“最后的问题” 打开两个宝箱，我们获得“枯竭的螺杯”和“学院某处的钥匙” 然后我们往外面走，找到无法打开的门，利用钥匙开门 门开之后即可获得隐藏成就【黑字的研究】",
    "length": 513
}