{
    "game_id": 2,
    "post_id": "51939691",
    "f_forum_id": 43,
    "subject": "【V4.6攻略】成就：为书所爱的人，8本遗落的魔导书及书架",
    "url": "https://www.miyoushe.com/ys/article/51939691",
    "created_at": 1713947318,
    "like_num": 1257,
    "view_num": 61762,
    "reply_num": 114,
    "text": "大家好，这里是抓马特鸡~ 本帖给大家带来V4.6版本 遗落的魔导书收集 玩法介绍 在褪色古堡中，按T可以将E技能切换为乐章之力。 神出鬼没的魔导书可以用 短按「乐章」 使其停止后拾取： 消耗拾取的魔导书开启书柜。 对开启书柜 长按「乐章」 之力，即可通过。 第一处 褪色古堡· 底层 。 书和书柜在同一位置。 书柜后能找到： 水神瞳*1，精致的宝箱*1 第二处 褪色古堡· 中层 。 最近的书架位置： 第三处 魔导书在褪色古堡· 底层 。 最近的书架位置： 书架后能找到： 精致的宝箱*1，摩拉盒*1 第四处 魔导书在褪色古堡· 底层 。 书架在褪色古堡· 中层 ——一个图书馆结构建筑的一楼。 书架后能找到： 奇馈宝箱*1，珍贵的宝箱*1， 央陆双手剑原胚*1 第五处 书本在褪色古堡· 中层 ——一个图书馆结构建筑的一楼。 书架在褪色古堡· 中层 。图书馆结构建筑的一、二楼之间。 书架后能找到： 精致的宝箱*1，宝箱中有 遗落的曲谱残页·其一 第六处 褪色古堡· 中层 。图书馆结构建筑的 二楼 。魔导书和书架都在一起。 书架后能找到： 精致的宝箱*1 第七处 在褪色古堡·中层。图书馆结构建筑的 二楼 。下图位置打晶体机关。 乘电梯向上（这个电梯换乘时不需要跳，等停稳时走过去就行，跳了反而容易掉下去）。 在中层处能捡到【北境秘史·卷三】。再触发这里的晶体机关继续向上。 来到顶层，有一本魔导书和魔导书架。 书架后能找到： 水神瞳*1，珍贵的宝箱*1，宝箱中有 遗落的曲谱残页·其二 第八处 在褪色古堡·陈列馆此处，跟随提示走到顶端。 刷出精致的宝箱后，可以看到一本魔导书出现在高处。 最靠近的书架位置： 书架后能找到： 珍贵的宝箱*1 收集完全部8本书，打开八个书柜，即可完成成就 为书所爱的人。",
    "length": 753
}