{
    "game_id": 2,
    "post_id": "39307720",
    "f_forum_id": 43,
    "subject": "10把绝版的四星武器，错过就真的错过了",
    "url": "https://www.miyoushe.com/ys/article/39307720",
    "created_at": 1683986798,
    "like_num": 4975,
    "view_num": 90263,
    "reply_num": 254,
    "text": "原神有一类武器是通过版本的限时活动送的，错过了就不再有， 目前还没有出现复刻的先例 ，因此可以说是绝版武器。截至3.6版本，一共有10把限定活动武器，今天就一起来看看吧。 一、腐殖之剑-1.2版本活动武器 这把武器的强度和泛用性还算不错，副词条是元素充能效率非常适合辅助和副C角色使用，比如班尼特、琴、行秋等。由于是1.2版本的限定武器，属于非常早期的版本，因此这把武器的持有人数并不多。本来这把武器是班尼特的最佳四星武器之一，而在须弥锻造单手剑原木刀出来之后，腐殖之剑就没那么香了。 二、风花之颂-1.4版本活动武器 这把武器强度和泛用性都非常一般，副词条是元素精通，被动仅仅是提升攻击力，提升的数值还非常少。相比绝弦、弓藏这类可以直接提供增伤的武器，可以说是被完爆了。 三、嘟嘟可故事集-1.6版本活动武器 从名字就可以看出来是为可莉制作的武器，外观和属性都和可莉相配。武器强度还算不错，适合用普通攻击和重击作为主要输出手段的站场法师使用，而且颜值也非常高，因此也成为了不少新手玩家都很想要的一个绝版武器。 四、衔珠海皇-2.1版本活动武器 衔珠海皇被不少玩家称作“咸鱼大剑”，迪卢克拿这把武器开大的时候，真是名副其实的“蒙德烤鱼”。这把武器观赏性高，但是强度和泛用性比较一般，属于大剑角色基本都能用，但都不怎么好用的那种，因此一般只推荐新手在过渡使用。 五、辰砂之纺锤-2.3版本活动武器 副词条为防御力加成，同时2.3版本正是阿贝多复刻的版本，因此这把武器其实就是为阿贝多定制的四星专武了。在强度上来看，这把武器给阿贝多用强度是非常高的，甚至就单论阿贝多E技能后台伤害看，这把武器是目前伤害最高的武器，打败了不少五星武器。 六、证誓之明瞳-2.5版本活动武器 证誓之明瞳外观非常好看，可以说是珊瑚宫心海的外观专武。不过这把武器的强度和泛用性都很差，跟心海完全不搭。目前能用这把武器的角色非常少，是一把更适合在仓库中当做收藏的绝版武器。 七、落霞-2.7版本活动武器 这把武器在四星武器中拥有比较高的白值，以及元素充能效率的副属性，被动是增伤效果，但是需要一定的启动时间。落霞属于很全面，但是又没有哪一项特别突出的武器，所以整体比较尴尬。目前最适合使用这把武器的是九条。 八、风信之锋-3.1版本活动武器 风信之锋目前的强度和泛用性都比较低，比较适合的是赛诺，可以作为过渡武器使用。武器提供大量的攻击力加成所以对于申鹤也是一种选择。 九、东花坊时雨-3.3版本活动武器 东花坊时雨由于它的造型，被玩家们又称为“鬼伞”。副词条和铁蜂刺一样提供165的元素精通，因此能用铁蜂刺的角色，也可以用鬼伞。比如妮露、万叶、久岐忍等。如果缺精通单手剑的话，鬼伞是很好的应急武器。 十、饰铁之花-3.5版本活动武器 副属性和被动都有元素精通加成，适合打反应输出的大剑角色。目前是彩虹雷泽，也就是玩剧变反应流雷泽的毕业武器。卡维也可以使用，提高自身精通与直伤。 目前还没有活动武器复刻的先例，未来也不太可能出现。唯一的可能是新增up限定武器，功能性和过去的活动武器类似，所以说什么时候新出一把防御单手剑？",
    "length": 1296
}